[
  {
    "id": 0,
    "sectionEs": "APLICACIONES WEB",
    "sectionEn": "WEB APPS",
    "projects": [
      {
        "id": 0,
        "name": "Weather forecast",
        "github": "https://github.com/diegopineda7/weather-forecast",
        "image": "weather",
        "frameworks": [
          "React JS",
          "Git"
        ],
        "descriptionEs": "Aplicación para ver el clima actual y el pronóstico para 3 días de Bogotá. Interfaz gráfica construida por disenador web.",
        "descriptionEn": "Application to see the current weather and the forescast for the next 3 days in Bogotá. User Interface build by a web designer.",
        "link": "https://github.com/diegopineda7/weather-forecast"
      },
      {
        "id": 1,
        "name": "Claudia (Chatbot)",
        "github": "",
        "image": "claudia",
        "frameworks": [
          "Node.js",
          "React JS",
          "PostgreSQL",
          "Git"
        ],
        "descriptionEs": "Chatbot para la comunicación entre estudiantes, profesores y personal administrativo del IPRED - UIS.",
        "descriptionEn": "Chatbot for communication between students, teachers and administrative staff of IPRED - UIS.",
        "link": "https://ipred.uis.edu.co/eisi/"
      },
      {
        "id": 2,
        "name": "Products App",
        "github": "https://github.com/diegopineda7/mern-products-app",
        "image": "store",
        "frameworks": [
          "Node.js",
          "React JS",
          "MongoDB",
          "Git"
        ],
        "descriptionEs": "Aplicación con REST API para agregar productos a una base de datos y mostrarlos en el front-end.",
        "descriptionEn": "Application with REST API to add products to a database and show them on the front-end.",
        "link": "https://mern-productsapp.herokuapp.com/"
      },
      {
        "id": 3,
        "name": "Portfolio",
        "github": "https://github.com/diegopineda7/portfolio",
        "image": "portfolio",
        "frameworks": [
          "Node.js",
          "React JS",
          "Git"
        ],
        "descriptionEs": "El portafolio que estás viendo. En él te muestro mis habilidades, mis proyectos y cómo podemos contactarnos.",
        "descriptionEn": "The portfolio you are viewing. In it I show you my skills, my projects and how we can contact each other.",
        "link": ""
      }
    ]
  },
  {
    "id": 1,
    "sectionEs": "APLICACIONES MOVILES",
    "sectionEn": "MOBILE APPS",
    "projects": [
      {
        "id": 0,
        "name": "YouTrain",
        "github": "",
        "image": "youtrain",
        "frameworks": [
          "Node.js",
          "React Native",
          "MongoDB",
          "Git"
        ],
        "descriptionEs": "App para crear un plan de entrenamiento personalizado con seguimiento de progreso según objetivo.",
        "descriptionEn": "App to create a personalized training plan with progress tracking according to goal.",
        "link": ""
      },
      {
        "id": 1,
        "name": "QR Attendance",
        "github": "",
        "image": "ipred",
        "frameworks": [
          "Node.js",
          "React Native",
          "React JS",
          "Google Sheets",
          "Git"
        ],
        "descriptionEs": "Lector QR para el control de asistencia al V Congreso Internacional en Regencia de Farmacia del IPRED - UIS.",
        "descriptionEn": "QR reader to control attendance at the V International Congress on Pharmacy Regency of IPRED - UIS.",
        "link": ""
      },
      {
        "id": 2,
        "name": "ProgressBuild",
        "github": "https://github.com/diegopineda7/ProgressBuild",
        "image": "progress",
        "frameworks": [
          "React Native",
          "MongoDB",
          "Git"
        ],
        "descriptionEs": "App para controlar el progreso en ejercicios de rutinas de entrenamiento.",
        "descriptionEn": "App to track the progress in training routines exercises.",
        "link": ""
      },
      {
        "id": 3,
        "name": "Contact App",
        "github": "https://github.com/diegopineda7/contact-manager",
        "image": "contact",
        "frameworks": [
          "React Native",
          "Firebase",
          "Git"
        ],
        "descriptionEs": "App de agenda de contactos con funcionalidad para llamar y enviar mensajes de texto.",
        "descriptionEn": "Address book app with functionality to call and send text messages.",
        "link": ""
      }
    ]
  }
]